SpaceFlow/SpaceFlow.py
SpaceFlow/__init__.py
SpaceFlow/util.py
SpaceFlow-1.0.4.dist-info/LICENSE
SpaceFlow-1.0.4.dist-info/METADATA
SpaceFlow-1.0.4.dist-info/WHEEL
SpaceFlow-1.0.4.dist-info/top_level.txt
SpaceFlow-1.0.4.dist-info/RECORD
