Metadata-Version: 2.1
Name: SpaceFlow
Version: 1.0.4
Summary: Identifying Spatiotemporal Patterns of Cells for Spatial Transcriptome Data
Author: Honglei Ren
Author-email: hongleir1@gmail.com
License-File: LICENSE
Requires-Dist: numpy
Requires-Dist: scipy
Requires-Dist: pandas
Requires-Dist: anndata
Requires-Dist: gudhi
Requires-Dist: matplotlib
Requires-Dist: networkx
Requires-Dist: notebook
Requires-Dist: scanpy
Requires-Dist: squidpy
Requires-Dist: scikit-learn
Requires-Dist: torch (>=1.9.0)
Requires-Dist: torch-geometric (>=1.7.2)
Requires-Dist: torch-sparse (>=0.6.11)
Requires-Dist: torch-scatter (>=2.0.8)
Requires-Dist: cmcrameri
